{
  "scores": [
    {
      "package": "truthbeam",
      "function": "(*Config).Validate",
      "file": "config.go",
      "line": 23,
      "complexity": 5,
      "line_coverage": 100,
      "crap": 5,
      "contract_coverage": 0,
      "gaze_crap": 30,
      "quadrant": "Q3_SimpleButUnderspecified"
    },
    {
      "package": "truthbeam",
      "function": "NewFactory",
      "file": "factory.go",
      "line": 20,
      "complexity": 1,
      "line_coverage": 100,
      "crap": 1,
      "contract_coverage": 0,
      "gaze_crap": 2,
      "quadrant": "Q1_Safe"
    },
    {
      "package": "truthbeam",
      "function": "createDefaultConfig",
      "file": "factory.go",
      "line": 27,
      "complexity": 1,
      "line_coverage": 100,
      "crap": 1
    },
    {
      "package": "truthbeam",
      "function": "createLogsProcessor",
      "file": "factory.go",
      "line": 43,
      "complexity": 2,
      "line_coverage": 0,
      "crap": 6
    },
    {
      "package": "applier",
      "function": "NewApplier",
      "file": "internal/applier/applier.go",
      "line": 19,
      "complexity": 1,
      "line_coverage": 100,
      "crap": 1,
      "contract_coverage": 0,
      "gaze_crap": 2,
      "quadrant": "Q1_Safe"
    },
    {
      "package": "applier",
      "function": "(*Applier).Apply",
      "file": "internal/applier/applier.go",
      "line": 27,
      "complexity": 7,
      "line_coverage": 100,
      "crap": 7,
      "contract_coverage": 0,
      "gaze_crap": 56,
      "quadrant": "Q3_SimpleButUnderspecified"
    },
    {
      "package": "applier",
      "function": "(*Applier).Extract",
      "file": "internal/applier/applier.go",
      "line": 68,
      "complexity": 7,
      "line_coverage": 90.47619047619048,
      "crap": 7.042328042328042,
      "contract_coverage": 0,
      "gaze_crap": 56,
      "quadrant": "Q3_SimpleButUnderspecified"
    },
    {
      "package": "applier",
      "function": "(Status).String",
      "file": "internal/applier/status.go",
      "line": 29,
      "complexity": 1,
      "line_coverage": 100,
      "crap": 1
    },
    {
      "package": "applier",
      "function": "parseResult",
      "file": "internal/applier/status.go",
      "line": 33,
      "complexity": 5,
      "line_coverage": 100,
      "crap": 5
    },
    {
      "package": "applier",
      "function": "mapResult",
      "file": "internal/applier/status.go",
      "line": 48,
      "complexity": 4,
      "line_coverage": 100,
      "crap": 4
    },
    {
      "package": "client",
      "function": "NewCacheableClient",
      "file": "internal/client/cacheable.go",
      "line": 30,
      "complexity": 4,
      "line_coverage": 87.5,
      "crap": 4.03125,
      "contract_coverage": 0,
      "gaze_crap": 20,
      "quadrant": "Q3_SimpleButUnderspecified"
    },
    {
      "package": "client",
      "function": "NewCacheableClientWithCache",
      "file": "internal/client/cacheable.go",
      "line": 49,
      "complexity": 1,
      "line_coverage": 100,
      "crap": 1,
      "contract_coverage": 0,
      "gaze_crap": 2,
      "quadrant": "Q1_Safe"
    },
    {
      "package": "client",
      "function": "cacheKey",
      "file": "internal/client/cacheable.go",
      "line": 58,
      "complexity": 1,
      "line_coverage": 100,
      "crap": 1
    },
    {
      "package": "client",
      "function": "(*CacheableClient).Retrieve",
      "file": "internal/client/cacheable.go",
      "line": 64,
      "complexity": 4,
      "line_coverage": 92.3076923076923,
      "crap": 4.007282658170232,
      "contract_coverage": 0,
      "gaze_crap": 20,
      "quadrant": "Q3_SimpleButUnderspecified"
    },
    {
      "package": "client",
      "function": "(*CacheableClient).callEnrich",
      "file": "internal/client/cacheable.go",
      "line": 98,
      "complexity": 5,
      "line_coverage": 92.3076923076923,
      "crap": 5.011379153390988
    },
    {
      "package": "client",
      "function": "(*otterCacheStore).Get",
      "file": "internal/client/otter.go",
      "line": 18,
      "complexity": 1,
      "line_coverage": 100,
      "crap": 1
    },
    {
      "package": "client",
      "function": "(*otterCacheStore).Set",
      "file": "internal/client/otter.go",
      "line": 22,
      "complexity": 1,
      "line_coverage": 100,
      "crap": 1
    },
    {
      "package": "client",
      "function": "(*otterCacheStore).Delete",
      "file": "internal/client/otter.go",
      "line": 27,
      "complexity": 1,
      "line_coverage": 0,
      "crap": 2
    },
    {
      "package": "client",
      "function": "NewOtterStore",
      "file": "internal/client/otter.go",
      "line": 32,
      "complexity": 1,
      "line_coverage": 100,
      "crap": 1,
      "contract_coverage": 0,
      "gaze_crap": 2,
      "quadrant": "Q1_Safe"
    },
    {
      "package": "truthbeam",
      "function": "newTruthBeamProcessor",
      "file": "processor.go",
      "line": 27,
      "complexity": 2,
      "line_coverage": 100,
      "crap": 2
    },
    {
      "package": "truthbeam",
      "function": "(*truthBeamProcessor).processLogs",
      "file": "processor.go",
      "line": 42,
      "complexity": 7,
      "line_coverage": 95.23809523809524,
      "crap": 7.005291005291006
    },
    {
      "package": "truthbeam",
      "function": "(*truthBeamProcessor).start",
      "file": "processor.go",
      "line": 84,
      "complexity": 4,
      "line_coverage": 72.72727272727273,
      "crap": 4.324567993989482
    }
  ],
  "summary": {
    "total_functions": 22,
    "avg_complexity": 3,
    "avg_line_coverage": 87.75258832077014,
    "avg_crap": 3.246459038780443,
    "crapload": 0,
    "crap_threshold": 15,
    "gaze_crapload": 5,
    "gaze_crap_threshold": 15,
    "avg_gaze_crap": 21.11111111111111,
    "avg_contract_coverage": 0,
    "quadrant_counts": {
      "Q1_Safe": 4,
      "Q3_SimpleButUnderspecified": 5
    },
    "worst_crap": [
      {
        "package": "applier",
        "function": "(*Applier).Extract",
        "file": "internal/applier/applier.go",
        "line": 68,
        "complexity": 7,
        "line_coverage": 90.47619047619048,
        "crap": 7.042328042328042,
        "contract_coverage": 0,
        "gaze_crap": 56,
        "quadrant": "Q3_SimpleButUnderspecified"
      },
      {
        "package": "truthbeam",
        "function": "(*truthBeamProcessor).processLogs",
        "file": "processor.go",
        "line": 42,
        "complexity": 7,
        "line_coverage": 95.23809523809524,
        "crap": 7.005291005291006
      },
      {
        "package": "applier",
        "function": "(*Applier).Apply",
        "file": "internal/applier/applier.go",
        "line": 27,
        "complexity": 7,
        "line_coverage": 100,
        "crap": 7,
        "contract_coverage": 0,
        "gaze_crap": 56,
        "quadrant": "Q3_SimpleButUnderspecified"
      },
      {
        "package": "truthbeam",
        "function": "createLogsProcessor",
        "file": "factory.go",
        "line": 43,
        "complexity": 2,
        "line_coverage": 0,
        "crap": 6
      },
      {
        "package": "client",
        "function": "(*CacheableClient).callEnrich",
        "file": "internal/client/cacheable.go",
        "line": 98,
        "complexity": 5,
        "line_coverage": 92.3076923076923,
        "crap": 5.011379153390988
      }
    ],
    "worst_gaze_crap": [
      {
        "package": "applier",
        "function": "(*Applier).Apply",
        "file": "internal/applier/applier.go",
        "line": 27,
        "complexity": 7,
        "line_coverage": 100,
        "crap": 7,
        "contract_coverage": 0,
        "gaze_crap": 56,
        "quadrant": "Q3_SimpleButUnderspecified"
      },
      {
        "package": "applier",
        "function": "(*Applier).Extract",
        "file": "internal/applier/applier.go",
        "line": 68,
        "complexity": 7,
        "line_coverage": 90.47619047619048,
        "crap": 7.042328042328042,
        "contract_coverage": 0,
        "gaze_crap": 56,
        "quadrant": "Q3_SimpleButUnderspecified"
      },
      {
        "package": "truthbeam",
        "function": "(*Config).Validate",
        "file": "config.go",
        "line": 23,
        "complexity": 5,
        "line_coverage": 100,
        "crap": 5,
        "contract_coverage": 0,
        "gaze_crap": 30,
        "quadrant": "Q3_SimpleButUnderspecified"
      },
      {
        "package": "client",
        "function": "NewCacheableClient",
        "file": "internal/client/cacheable.go",
        "line": 30,
        "complexity": 4,
        "line_coverage": 87.5,
        "crap": 4.03125,
        "contract_coverage": 0,
        "gaze_crap": 20,
        "quadrant": "Q3_SimpleButUnderspecified"
      },
      {
        "package": "client",
        "function": "(*CacheableClient).Retrieve",
        "file": "internal/client/cacheable.go",
        "line": 64,
        "complexity": 4,
        "line_coverage": 92.3076923076923,
        "crap": 4.007282658170232,
        "contract_coverage": 0,
        "gaze_crap": 20,
        "quadrant": "Q3_SimpleButUnderspecified"
      }
    ]
  }
}
